b2c_tms_wrapper/__init__.py
b2c_tms_wrapper/error.py
b2c_tms_wrapper/models.py
b2c_tms_wrapper/timeout.py
b2c_tms_wrapper/utils.py
b2c_tms_wrapper/services/__init__.py
b2c_tms_wrapper/services/b2c_tms.py
b2c_tms_wrapper/services/booking_history.py
b2c_tms_wrapper/services/booking_opening_times.py
b2c_tms_wrapper/services/booking_requests.py
b2c_tms_wrapper/services/reservations.py
b2c_tms_wrapper/services/tracking_details.py
b2c_tms_wrapper/services/trip_events.py
b2c_tms_wrapper/services/trips.py
b2c_tms_wrapper/services/user_journeys.py
tests/__init__.py
tests/factories.py
tests/test_booking_history.py
tests/test_booking_opening_times.py
tests/test_booking_requests.py
tests/test_models.py
tests/test_reservations.py
tests/test_tracking_details.py
tests/test_trip_events.py
tests/test_trips.py
tests/test_user_journeys.py
b2c_tms_wrapper-0.0.4.dist-info/METADATA
b2c_tms_wrapper-0.0.4.dist-info/WHEEL
b2c_tms_wrapper-0.0.4.dist-info/top_level.txt
b2c_tms_wrapper-0.0.4.dist-info/RECORD
